beetsplug/mpdqueue.py
beets_mpdqueue-0.3.0.dist-info/METADATA
beets_mpdqueue-0.3.0.dist-info/WHEEL
beets_mpdqueue-0.3.0.dist-info/licenses/LICENSE
beets_mpdqueue-0.3.0.dist-info/RECORD
