Metadata-Version: 2.4
Name: beets-mpdqueue
Version: 0.3.0
Summary: Beets plugin to add imported files to MPD queue
Project-URL: Repository, https://github.com/Hamuko/beets-mpdqueue
Author-email: Hamuko <hamuko@burakku.com>
License-Expression: Apache-2.0
License-File: LICENSE
Requires-Python: >=3.9
Requires-Dist: beets>=2.3.0
